cz_light_gitmoji/__init__.py
cz_light_gitmoji/conventional_gitmojis_info.txt
cz_light_gitmoji/main.py
cz_light_gitmoji/py.typed
gitmojify/__init__.py
gitmojify/mojify.py
gitmojify/py.typed
shared/__init__.py
shared/gitmojis.py
shared/model.py
shared/py.typed
shared/spec.py
shared/utils.py
cz_light_conventional_gitmoji-0.3.3.dist-info/METADATA
cz_light_conventional_gitmoji-0.3.3.dist-info/WHEEL
cz_light_conventional_gitmoji-0.3.3.dist-info/entry_points.txt
cz_light_conventional_gitmoji-0.3.3.dist-info/RECORD
