Metadata-Version: 2.4
Name: cz-light-conventional-gitmoji
Version: 0.3.3
Summary: A commitizen plugin that combines gitmoji and conventional commits in a lightweight way.
Author-email: sasirven <77392535+sasirven@users.noreply.github.com>
License: MIT
Requires-Python: >=3.9
Requires-Dist: commitizen>=4.8.3
Requires-Dist: typing-extensions>=4.14.0; python_version > '3.10'
